validantor/__init__.py
validantor/has_unique_elements.py
validantor/is_in_range.py
validantor/is_string_length.py
validantor/is_type.py
validantor-0.1.0.dist-info/METADATA
validantor-0.1.0.dist-info/WHEEL
validantor-0.1.0.dist-info/top_level.txt
validantor-0.1.0.dist-info/RECORD
