Metadata-Version: 2.1
Name: validantor
Version: 0.1.0
Summary: A simple data validation library in Python.
Home-page: https://github.com
Author: Daniel Soto
Author-email: dansoto804@gmail.com
Classifier: Programming Language :: Python :: 3
Classifier: License :: OSI Approved :: MIT License
Classifier: Operating System :: OS Independent
Requires-Python: >=3.6
